spirit/Spirit.dll
spirit/__init__.py
spirit/chain.py
spirit/configuration.py
spirit/constants.py
spirit/geometry.py
spirit/hamiltonian.py
spirit/htst.py
spirit/io.py
spirit/log.py
spirit/quantities.py
spirit/scalar.py
spirit/simulation.py
spirit/spiritlib.py
spirit/state.py
spirit/system.py
spirit/transition.py
spirit/version.py
spirit/parameters/__init__.py
spirit/parameters/ema.py
spirit/parameters/gneb.py
spirit/parameters/llg.py
spirit/parameters/mc.py
spirit/parameters/mmf.py
spirit-2.2.0.dist-info/LICENSE.txt
spirit-2.2.0.dist-info/METADATA
spirit-2.2.0.dist-info/WHEEL
spirit-2.2.0.dist-info/top_level.txt
spirit-2.2.0.dist-info/RECORD
