Metadata-Version: 2.1
Name: spirit
Version: 2.2.0
Summary: Optimizations and Dynamics Framework for atomistic Spin systems
Home-page: https://spirit-code.github.io
Author: Gideon Mueller
Author-email: g.mueller@fz-juelich.de
Maintainer: Gideon Mueller
Maintainer-email: g.mueller@fz-juelich.de
License: MIT
Keywords: Spirit,Spin Dynamics
Classifier: Development Status :: 4 - Beta
Classifier: Intended Audience :: Science/Research
Classifier: Natural Language :: English
Classifier: License :: OSI Approved :: MIT License
Classifier: Operating System :: OS Independent
Classifier: Programming Language :: C
Classifier: Programming Language :: C++
Classifier: Programming Language :: Python
Classifier: Topic :: Scientific/Engineering
Classifier: Topic :: Software Development :: Libraries :: Python Modules
License-File: LICENSE.txt
Requires-Dist: numpy
